pyaims/__init__.py
pyaims/aims_input.py
pyaims/calculation.py
pyaims/errors.py
pyaims/cli/__init__.py
pyaims/control/__init__.py
pyaims/control/chunk.py
pyaims/control/control.py
pyaims/control/cube.py
pyaims/control/kpoints.py
pyaims/geometry/__init__.py
pyaims/geometry/atom.py
pyaims/geometry/geometry.py
pyaims/output_parser/__init__.py
pyaims/output_parser/aims_out_calculation_section.py
pyaims/output_parser/aims_out_header_section.py
pyaims/output_parser/aims_out_section.py
pyaims/output_parser/aims_outputs.py
pyaims/outputs/__init__.py
pyaims/outputs/band_structure.py
pyaims/outputs/stdout.py
pyaims/outputs/parser/__init__.py
pyaims/outputs/parser/abc.py
pyaims/outputs/parser/converters.py
pyaims/outputs/parser/parsers.py
pyaims/outputs/parser/utils.py
pyaims/species_defaults/__init__.py
pyaims/species_defaults/basis_function.py
pyaims/species_defaults/basis_set.py
pyaims/species_defaults/electronic_configuration.py
pyaims/species_defaults/integration_grid.py
pyaims/species_defaults/species.py
pyaims/utils/__init__.py
pyaims/utils/typecast.py
tests/__init__.py
tests/conftest.py
tests/test_basis_function.py
tests/test_basis_set.py
tests/test_electronic_configuration.py
tests/test_integration_grid.py
tests/test_stdout.py
tests/test_typecast.py
tests/utils.py
tests/test_inputs/test_control.py
tests/test_inputs/test_geometry.py
tests/test_parsers/test_parser.py
tests/test_parsers/test_sections.py
pyaims-0.0.2.dist-info/METADATA
pyaims-0.0.2.dist-info/WHEEL
pyaims-0.0.2.dist-info/top_level.txt
pyaims-0.0.2.dist-info/RECORD
